{
  "magic": "E!vIA5L86J2I",
  "timestamp": "2021-06-06T00:49:25.534907+00:00",
  "repo": "martinduke/draft-ietf-shmoo-cancel-meeting",
  "labels": [
    {
      "name": "bug",
      "description": "Something isn't working",
      "color": "d73a4a"
    },
    {
      "name": "documentation",
      "description": "Improvements or additions to documentation",
      "color": "0075ca"
    },
    {
      "name": "duplicate",
      "description": "This issue or pull request already exists",
      "color": "cfd3d7"
    },
    {
      "name": "enhancement",
      "description": "New feature or request",
      "color": "a2eeef"
    },
    {
      "name": "help wanted",
      "description": "Extra attention is needed",
      "color": "008672"
    },
    {
      "name": "good first issue",
      "description": "Good for newcomers",
      "color": "7057ff"
    },
    {
      "name": "invalid",
      "description": "This doesn't seem right",
      "color": "e4e669"
    },
    {
      "name": "question",
      "description": "Further information is requested",
      "color": "d876e3"
    },
    {
      "name": "wontfix",
      "description": "This will not be worked on",
      "color": "ffffff"
    }
  ],
  "issues": [
    {
      "number": 1,
      "id": "MDU6SXNzdWU2ODI5NTEyODA=",
      "title": "Converge with 109 Criteria",
      "url": "https://github.com/martinduke/draft-ietf-shmoo-cancel-meeting/issues/1",
      "state": "OPEN",
      "author": "martinduke",
      "authorAssociation": "OWNER",
      "assignees": [],
      "labels": [],
      "body": "Mirja points out that the 109 criteria (https://www.ietf.org/how/meetings/109/assessment-framework-person-vs-online-ietf-109-meeting) has diverged a bit from the draft, which is based on 108. Some concrete examples:\r\n\r\n- Quarantine requirements are not listed anywhere\r\n- \"inherently discriminatory\" travel restrictions. (On this one, I'm not sure how to build a general priniciple out of this -- many countries have discriminatory entry policies if you look hard enough).\r\n- if national bans or extraordinary airfare increases exclude over 20% of expected attendees (based on historical data for events in that region)\r\n- mass gatherings of less than 500 people are allowed.\r\n\r\n",
      "createdAt": "2020-08-20T17:36:22Z",
      "updatedAt": "2020-08-20T17:36:22Z",
      "closedAt": null,
      "comments": []
    },
    {
      "number": 2,
      "id": "MDU6SXNzdWU2ODI5NTE5Nzg=",
      "title": "Add local authorities",
      "url": "https://github.com/martinduke/draft-ietf-shmoo-cancel-meeting/issues/2",
      "state": "OPEN",
      "author": "martinduke",
      "authorAssociation": "OWNER",
      "assignees": [],
      "labels": [],
      "body": "Add the local authorities, not just US and UK travel advisories.",
      "createdAt": "2020-08-20T17:37:04Z",
      "updatedAt": "2020-08-20T17:37:04Z",
      "closedAt": null,
      "comments": []
    },
    {
      "number": 3,
      "id": "MDU6SXNzdWU4MzQyNTM0NTg=",
      "title": "Comments from IETF110",
      "url": "https://github.com/martinduke/draft-ietf-shmoo-cancel-meeting/issues/3",
      "state": "CLOSED",
      "author": "martinduke",
      "authorAssociation": "OWNER",
      "assignees": [],
      "labels": [],
      "body": "Thread starts here: https://mailarchive.ietf.org/arch/msg/manycouches/pIaIKX3OqHOND5w4uJGOWhbdmCQ/",
      "createdAt": "2021-03-17T23:27:00Z",
      "updatedAt": "2021-06-02T18:56:59Z",
      "closedAt": "2021-06-02T18:56:59Z",
      "comments": [
        {
          "author": "martinduke",
          "authorAssociation": "OWNER",
          "body": "Fixed by #4",
          "createdAt": "2021-06-02T18:56:59Z",
          "updatedAt": "2021-06-02T18:56:59Z"
        }
      ]
    }
  ],
  "pulls": [
    {
      "number": 4,
      "id": "MDExOlB1bGxSZXF1ZXN0NjAzMjUyNDQ5",
      "title": "ietf110 comments",
      "url": "https://github.com/martinduke/draft-ietf-shmoo-cancel-meeting/pull/4",
      "state": "MERGED",
      "author": "martinduke",
      "authorAssociation": "OWNER",
      "assignees": [],
      "labels": [],
      "body": "draft -01",
      "createdAt": "2021-03-30T00:14:59Z",
      "updatedAt": "2021-03-30T02:01:20Z",
      "baseRepository": "martinduke/draft-ietf-shmoo-cancel-meeting",
      "baseRefName": "master",
      "baseRefOid": "f1880fc1c87b75e534562e302c6cf9d37f60b5b6",
      "headRepository": "martinduke/draft-ietf-shmoo-cancel-meeting",
      "headRefName": "110-comments",
      "headRefOid": "4a392843fa3f8d2c3aff0e361fbe852f48d8931b",
      "closedAt": "2021-03-30T00:15:04Z",
      "mergedAt": "2021-03-30T00:15:04Z",
      "mergedBy": "martinduke",
      "mergeCommit": {
        "oid": "d5f8bab07708cc14c04673d8e546cd1e4583b62a"
      },
      "comments": [],
      "reviews": []
    }
  ]
}